azurestoragewrap/__init__.py
azurestoragewrap/blob.py
azurestoragewrap/encryption.py
azurestoragewrap/exception.py
azurestoragewrap/queue.py
azurestoragewrap/snippets.py
azurestoragewrap/table.py
azurestoragewrap-0.2.22.dist-info/LICENSE.txt
azurestoragewrap-0.2.22.dist-info/METADATA
azurestoragewrap-0.2.22.dist-info/WHEEL
azurestoragewrap-0.2.22.dist-info/top_level.txt
azurestoragewrap-0.2.22.dist-info/RECORD
