Metadata-Version: 2.1
Name: azurestoragewrap
Version: 0.2.22
Summary: A Python Wrapper for modeling client side encrypted azure storage tables, queues and blobs
Home-page: https://github.com/omza/azurestoragewrap
Author: app workshop UG (haftungsbeschränkt)
Author-email: oliver@app-workshop.de
License: UNKNOWN
Keywords: azure storage model table blob queue wrapper
Platform: UNKNOWN
Classifier: Development Status :: 4 - Beta
Classifier: Intended Audience :: Developers
Classifier: Topic :: Software Development :: Libraries :: Python Modules
Classifier: License :: OSI Approved :: MIT License
Classifier: Programming Language :: Python :: 3
Requires-Dist: azure-storage
